onf_parser/__init__.py
onf_parser/models.py
onf_parser/parse.py
onf_parser-0.2.3.dist-info/AUTHORS.rst
onf_parser-0.2.3.dist-info/LICENSE.txt
onf_parser-0.2.3.dist-info/METADATA
onf_parser-0.2.3.dist-info/WHEEL
onf_parser-0.2.3.dist-info/top_level.txt
onf_parser-0.2.3.dist-info/RECORD
