Metadata-Version: 2.1
Name: onf-parser
Version: 0.2.3
Summary: OntoNotes Normal Form Parser
Home-page: https://github.com/lgessler/onf-parser
Author: Luke Gessler
Author-email: lukegessler@gmail.com
License: mit
Project-URL: Documentation, https://github.com/lgessler/onf-parser
Platform: any
Classifier: Development Status :: 4 - Beta
Classifier: Programming Language :: Python
Classifier: Programming Language :: Python :: 3
Requires-Python: >=3.7
License-File: LICENSE.txt
License-File: AUTHORS.rst
Requires-Dist: nltk
Provides-Extra: testing
Requires-Dist: pytest ; extra == 'testing'
Requires-Dist: pytest-cov ; extra == 'testing'
Requires-Dist: sphinx-rtd-theme ; extra == 'testing'
